MANIFEST.in
README.rst
setup.cfg
setup.py
jobarchitect/__init__.py
jobarchitect/agent.py
jobarchitect/backends.py
jobarchitect/sketchjob.py
jobarchitect/utils.py
jobarchitect.egg-info/PKG-INFO
jobarchitect.egg-info/SOURCES.txt
jobarchitect.egg-info/dependency_links.txt
jobarchitect.egg-info/entry_points.txt
jobarchitect.egg-info/requires.txt
jobarchitect.egg-info/top_level.txt
jobarchitect/templates/bash_job.sh.j2
jobarchitect/templates/basic_bash_script.sh.j2
jobarchitect/templates/docker_job.sh.j2
jobarchitect/templates/singularity_job.sh.j2
jobarchitect/templates/slurm_options.j2
jobarchitect/templates/slurm_script_multiple.slurm.j2
jobarchitect/templates/slurm_script_single.slurm.j2