Metadata-Version: 1.1
Name: jobarchitect
Version: 0.4.0
Summary: Tools for batching jobs and dealing with file paths
Home-page: https://github.com/JIC-CSB/jobarchitect
Author: Tjelvar Olsson
Author-email: tjelvar.olsson@jic.ac.uk
License: MIT
Download-URL: https://github.com/JIC-CSB/jobarchitect/tarball/0.4.0
Platform: UNKNOWN
